pica/ArcCosNode.py
pica/ArcSinNode.py
pica/ArcTanNode.py
pica/CosNode.py
pica/CoshNode.py
pica/CotNode.py
pica/CscNode.py
pica/DivNode.py
pica/ExpNode.py
pica/Graph.py
pica/LnNode.py
pica/LogNode.py
pica/MultNode.py
pica/Node.py
pica/PowerNode.py
pica/SecNode.py
pica/SinNode.py
pica/SinhNode.py
pica/SubNode.py
pica/SubsNode.py
pica/SumNode.py
pica/TanNode.py
pica/TanhNode.py
pica/ValueNode.py
pica/VariableNode.py
pica/__init__.py
picalib-0.6.0.dist-info/LICENSE
picalib-0.6.0.dist-info/METADATA
picalib-0.6.0.dist-info/WHEEL
picalib-0.6.0.dist-info/top_level.txt
picalib-0.6.0.dist-info/RECORD
