Metadata-Version: 2.1
Name: picalib
Version: 0.6.0
Summary: PiCa is lightweight and minimalist package for autodiff.
Author: Phikat
License-File: LICENSE
Requires-Dist: networkx
Requires-Dist: matplotlib
